pytest_jtl_collector/__init__.py
pytest_jtl_collector/plugin.py
pytest_jtl_collector-0.0.1.dist-info/LICENSE
pytest_jtl_collector-0.0.1.dist-info/METADATA
pytest_jtl_collector-0.0.1.dist-info/WHEEL
pytest_jtl_collector-0.0.1.dist-info/entry_points.txt
pytest_jtl_collector-0.0.1.dist-info/top_level.txt
pytest_jtl_collector-0.0.1.dist-info/RECORD
