Metadata-Version: 2.1
Name: pytest-jtl-collector
Version: 0.0.1
Summary: A simple plugin to use with pytest
Author-email: kyzhangs <kyzhangs@foxmail.com>
Maintainer-email: kyzhangs <kyzhangs@foxmail.com>
License: 
Project-URL: Repository, https://github.com/kyzhangs/pytest-jtl-collector
Classifier: Framework :: Pytest
Classifier: Development Status :: 4 - Beta
Classifier: Intended Audience :: Developers
Classifier: Topic :: Software Development :: Testing
Classifier: Operating System :: OS Independent
Classifier: Programming Language :: Python
Classifier: Programming Language :: Python :: 3.8
Classifier: Programming Language :: Python :: 3.9
Classifier: Programming Language :: Python :: 3.10
Classifier: Programming Language :: Python :: 3.11
Classifier: Programming Language :: Python :: 3.12
Classifier: Programming Language :: Python :: 3 :: Only
Classifier: Programming Language :: Python :: Implementation :: CPython
Classifier: Programming Language :: Python :: Implementation :: PyPy
Classifier: License :: OSI Approved :: Apache Software License
Requires-Python: >=3.8
License-File: LICENSE
Requires-Dist: pytest >=7.2.1
